gusty/__init__.py
gusty/building.py
gusty/errors.py
gusty/external_sensor.py
gusty/importing.py
gusty/multi.py
gusty/cli/__init__.py
gusty/cli/sample_tasks.py
gusty/cli/utils.py
gusty/parsing/__init__.py
gusty/parsing/loaders.py
gusty/parsing/parsers.py
gusty/parsing/utils.py
gusty/utils/__init__.py
gusty/utils/context.py
gusty-0.23.0.dist-info/licenses/LICENSE
tests/__init__.py
tests/test_adjusted_behavior.py
tests/test_cli.py
tests/test_context.py
tests/test_create_dags.py
tests/test_custom_operators.py
tests/test_default_behavior.py
tests/test_external_deps.py
tests/test_ignore_subfolders.py
tests/test_importing.py
tests/test_leaves_from_dict.py
tests/test_loader.py
tests/test_multi_task.py
tests/test_no_dir.py
tests/test_no_render_on_create.py
tests/test_parsing.py
tests/test_python_tasks.py
tests/test_task_group_dependencies.py
gusty-0.23.0.dist-info/METADATA
gusty-0.23.0.dist-info/WHEEL
gusty-0.23.0.dist-info/entry_points.txt
gusty-0.23.0.dist-info/top_level.txt
gusty-0.23.0.dist-info/RECORD
