Metadata-Version: 2.4
Name: gusty
Version: 0.23.0
Summary: Making DAG construction easier
Home-page: https://github.com/pipeline-tools/gusty
Author: Chris Cardillo, Michael Chow, David Robinson
Author-email: cfcardillo23@gmail.com
Classifier: Programming Language :: Python :: 3
Classifier: License :: OSI Approved :: MIT License
Classifier: Operating System :: OS Independent
Requires-Python: >=3.6
License-File: LICENSE
Requires-Dist: ABSQL
Requires-Dist: apache-airflow
Requires-Dist: click
Requires-Dist: inflection
Requires-Dist: jupytext
Requires-Dist: nbformat
Requires-Dist: pendulum
Requires-Dist: PyYaml
Dynamic: author
Dynamic: author-email
Dynamic: classifier
Dynamic: description
Dynamic: description-content-type
Dynamic: home-page
Dynamic: license-file
Dynamic: requires-dist
Dynamic: requires-python
Dynamic: summary
